[
  {
    "name": "Aerate",
    "initialFans": 155438079,
    "currentFans": 178723423
  },
  {
    "name": "KAKO",
    "initialFans": 153495860,
    "currentFans": 181244749
  },
  {
    "name": "Cheek",
    "initialFans": 150229874,
    "currentFans": 179184317
  },
  {
    "name": "motbob",
    "initialFans": 142908071,
    "currentFans": 167331056
  },
  {
    "name": "Keeves",
    "initialFans": 122586615,
    "currentFans": 143690877
  },
  {
    "name": "SHG",
    "initialFans": 124270163,
    "currentFans": 138699103
  },
  {
    "name": "Vetala",
    "initialFans": 118599120,
    "currentFans": 145636805
  },
  {
    "name": "zee",
    "initialFans": 118978625,
    "currentFans": 137858260
  },
  {
    "name": "Bagel",
    "initialFans": 112447158,
    "currentFans": 130427989
  },
  {
    "name": "Jaya",
    "initialFans": 109362165,
    "currentFans": 128798554
  },
  {
    "name": "crabitalism",
    "initialFans": 104746272,
    "currentFans": 121600978
  },
  {
    "name": "Carrot",
    "initialFans": 97781113,
    "currentFans": 123726884
  },
  {
    "name": "kaycey",
    "initialFans": 97133726,
    "currentFans": 117956284
  },
  {
    "name": "Fabino",
    "initialFans": 98949549,
    "currentFans": 120045136
  },
  {
    "name": "Xariesz",
    "initialFans": 95433437,
    "currentFans": 117315943
  },
  {
    "name": "YukariEX",
    "initialFans": 90425686,
    "currentFans": 119645040
  },
  {
    "name": "shadow",
    "initialFans": 88007330,
    "currentFans": 111110414
  },
  {
    "name": "Serac",
    "initialFans": 88088345,
    "currentFans": 103251636
  },
  {
    "name": "loonafreya",
    "initialFans": 64095059,
    "currentFans": 108619790
  },
  {
    "name": "HyuzShowSpeed",
    "initialFans": 81217690,
    "currentFans": 97514775
  },
  {
    "name": "Junyuu",
    "initialFans": 89167589,
    "currentFans": 90256918
  },
  {
    "name": "Biggiebudeater",
    "initialFans": 77654121,
    "currentFans": 94894828
  },
  {
    "name": "Yoseph",
    "initialFans": 77201339,
    "currentFans": 94795463
  },
  {
    "name": "Tymonji",
    "initialFans": 70272165,
    "currentFans": 90834340
  },
  {
    "name": "MAO",
    "initialFans": 66251143,
    "currentFans": 80191983
  },
  {
    "name": "Hilaos",
    "initialFans": 68912133,
    "currentFans": 82082368
  },
  {
    "name": "eric",
    "initialFans": 57850255,
    "currentFans": 74547358
  },
  {
    "name": "Pogka",
    "initialFans": 58486709,
    "currentFans": 76971895
  },
  {
    "name": "Xvious",
    "initialFans": 51142323,
    "currentFans": 60351810
  },
  {
    "name": "lie",
    "initialFans": 40911232,
    "currentFans": 56676500
  }
]
